pyrobase/__init__.py
pyrobase/bencode.py
pyrobase/fmt.py
pyrobase/iterutil.py
pyrobase/logutil.py
pyrobase/osutil.py
pyrobase/parts.py
pyrobase/pyutil.py
pyrobase/templating.py
pyrobase/testing.py
pyrobase/io/__init__.py
pyrobase/io/http.py
pyrobase/io/xmlrpc2scgi.py
pyrobase/paver/__init__.py
pyrobase/paver/documentation.py
pyrobase/paver/easy.py
pyrobase/paver/housekeeping.py
pyrobase/paver/quality.py
pyrobase/paver/support.py
pyrobase/webservice/__init__.py
pyrobase/webservice/imgur.py
pyrobase-0.5.2.data/data/EGG-INFO/LICENSE
pyrobase-0.5.2.data/data/EGG-INFO/README.rst
pyrobase-0.5.2.data/data/EGG-INFO/changelog
pyrobase-0.5.2.dist-info/DESCRIPTION.rst
pyrobase-0.5.2.dist-info/METADATA
pyrobase-0.5.2.dist-info/RECORD
pyrobase-0.5.2.dist-info/WHEEL
pyrobase-0.5.2.dist-info/metadata.json
pyrobase-0.5.2.dist-info/top_level.txt
pyrobase-0.5.2.dist-info/zip-safe
