Metadata-Version: 2.0
Name: pyrobase
Version: 0.5.2
Summary: PyroBase - General Python Helpers and Utilities
Home-page: https://github.com/pyroscope/pyrobase
Author: The PyroScope Project
Author-email: pyroscope.project@gmail.com
License: Copyright (c) 2011-2018 The PyroScope Project <pyroscope.project@gmail.com>
Keywords: python utility library paver unittests
Platform: UNKNOWN
Classifier: Development Status :: 5 - Production/Stable
Classifier: Intended Audience :: Developers
Classifier: License :: OSI Approved :: GNU General Public License (GPL)
Classifier: Natural Language :: English
Classifier: Operating System :: OS Independent
Classifier: Programming Language :: Python :: 2.7
Classifier: Topic :: Software Development :: Libraries :: Python Modules
Classifier: Topic :: Utilities
Requires-Dist: six
Provides-Extra: imgur
Requires-Dist: imgurpython; extra == 'imgur'
Requires-Dist: requests; extra == 'imgur'
Provides-Extra: imgur_ssl
Requires-Dist: imgurpython; extra == 'imgur_ssl'
Requires-Dist: requests[security]; extra == 'imgur_ssl'
